{"acat.md":"Clm86rYg","ais25.md":"DCiaFtUr","appendices.md":"bCejSIYy","changelog.md":"CfXeyTv2","ctd25.md":"DmDE_c-X","guide_installation.md":"CPIuHlAd","guide_introduction.md":"CwZmoVWZ","guide_quickstart.md":"DrSmQlmX","guide_remote-simulation.md":"CCAokRET","guide_simulation.md":"Bjbg8VWf","guide_tasks.md":"CkvnFp1o","index.md":"wvIhANgK","internal_admin.md":"BFtIfXu6","internal_backend.md":"C737gfJA","internal_container-image.md":"DDHempWP","internal_deployment.md":"BicP0f46","internal_overview.md":"DrFM558z","internal_sfapi.md":"BCenDqYT","library_benchmarks.md":"CL1mp8uk","library_cli.md":"DKfcjnBS","library_exploding.md":"eNTze1xS","library_loading.md":"G35VeW46","library_overview.md":"CHzIm0An","library_physics.md":"CKMCMUWs","library_remote.md":"BtX3RFIC","library_simulate.md":"CnO8NiRj","library_tasks.md":"C-w4k_m2","spaces_event-display.md":"CdHDpeeO","spaces_leaderboard.md":"C133ric1","spaces_model-zoo.md":"BvAF8a5C","spaces_overview.md":"DCqF0FSv","spaces_simulation-form.md":"C71Qh9WQ"}
