{"acat.md":"DFqrhWxl","ais25.md":"xzrgErLA","appendices.md":"xSKS3u2v","changelog.md":"C4xj5iH7","ctd25.md":"BnC_a8wC","guide_installation.md":"D1gclOyN","guide_introduction.md":"CmjRI9s6","guide_quickstart.md":"DkLaXJUm","guide_remote-simulation.md":"BCE8ox9E","guide_simulation.md":"ADP9czz2","guide_tasks.md":"CxHbBp_n","guide_tutorial.md":"yU4jjG8n","index.md":"GbVomP5r","internal_admin.md":"C1ZFkrk7","internal_backend.md":"bdPpHmHA","internal_container-image.md":"BmXeEr-k","internal_deployment.md":"DYj7zfne","internal_overview.md":"oPuECTdE","internal_sfapi.md":"C9LCOSsD","library_benchmarks.md":"CIkswgBx","library_cli.md":"DyHYlUfx","library_exploding.md":"QfSbrRXK","library_loading.md":"BVtLyrIg","library_overview.md":"BoR4SSzx","library_physics.md":"lMjA8Je_","library_remote.md":"CUvJX_JP","library_simulate.md":"D7X5wuUL","library_tasks.md":"BatdB7p2","spaces_event-display.md":"yfW9xdwJ","spaces_leaderboard.md":"CF4gwVWs","spaces_model-zoo.md":"ClCodI2x","spaces_overview.md":"Dd8Rsl3s","spaces_simulation-form.md":"Bw56UVLO"}
